cdm_client/__init__.py
cdm_client/cdm_client.py
cdm_client/config.py
cdm_client/database_adapter.py
cdm_client/qbittorrent_adapter.py
cdm_client/torent_client_factory.py
cdm_client/torrent_client_adapter_base.py
cdm_client/transmission_adapter.py
cdmclient-1.0.1.dist-info/licenses/LICENSE
cdmclient-1.0.1.dist-info/METADATA
cdmclient-1.0.1.dist-info/WHEEL
cdmclient-1.0.1.dist-info/entry_points.txt
cdmclient-1.0.1.dist-info/top_level.txt
cdmclient-1.0.1.dist-info/RECORD
