Metadata-Version: 2.4
Name: CDMClient
Version: 1.0.1
Summary: CDMClient
Author-email: Aron Radics <radics.aron.jozsef@gmail.com>
Project-URL: Homepage, https://github.com/radaron/CDMClient
Project-URL: Repository, https://github.com/radaron/CDMClient
Classifier: Programming Language :: Python :: 3
Classifier: Operating System :: OS Independent
Requires-Python: >=3.9
License-File: LICENSE
Requires-Dist: requests
Requires-Dist: transmission_rpc
Requires-Dist: cryptography
Requires-Dist: sqlalchemy>=2.0.0
Requires-Dist: qbittorrent-api>=2025.7.0
Dynamic: license-file
